playwright_localstorage/__init__.py
playwright_localstorage/async_.py
playwright_localstorage/base.py
playwright_localstorage/sync_.py
playwright_localstorage-1.1.0.dist-info/LICENSE
playwright_localstorage-1.1.0.dist-info/METADATA
playwright_localstorage-1.1.0.dist-info/WHEEL
playwright_localstorage-1.1.0.dist-info/RECORD
