Metadata-Version: 2.1
Name: playwright-localstorage
Version: 1.1.0
Summary: Extension for the Playwright package that allows access to the Web Storage API.
Home-page: https://pypi.org/project/playwright-localstorage/
License: MIT
Keywords: Playwright,Web Storage API,Poetry
Author: Dmitry Vasiliev
Author-email: contact.vasiliev.dmitry@gmail.com
Requires-Python: >=3.9,<4.0
Classifier: Framework :: AsyncIO
Classifier: License :: OSI Approved :: MIT License
Classifier: Operating System :: OS Independent
Classifier: Programming Language :: Python :: 3
Classifier: Programming Language :: Python :: 3.9
Classifier: Programming Language :: Python :: 3.10
Classifier: Programming Language :: Python :: 3.11
Classifier: Programming Language :: Python :: 3.12
Classifier: Programming Language :: Python :: 3.13
Classifier: Topic :: Internet :: WWW/HTTP :: Browsers
Classifier: Topic :: Software Development :: Testing
Requires-Dist: playwright (==1.*)
Project-URL: Documentation, https://github.com/swimmwatch/playwright-localstorage
Project-URL: Repository, https://github.com/swimmwatch/playwright-localstorage
